whack_a_mole/__init__.py
whack_a_mole/game.py
whack_a_mole-0.1.0.dist-info/METADATA
whack_a_mole-0.1.0.dist-info/WHEEL
whack_a_mole-0.1.0.dist-info/entry_points.txt
whack_a_mole-0.1.0.dist-info/top_level.txt
whack_a_mole-0.1.0.dist-info/RECORD
